CHANGES.rst
MANIFEST.in
README.rst
setup.cfg
setup.py
docs/CoNLL2002.rst
docs/Makefile
docs/api.rst
docs/changes.rst
docs/conf.py
docs/contributing.rst
docs/index.rst
docs/install.rst
docs/make.bat
docs/tutorial.rst
sklearn_crfsuite/__init__.py
sklearn_crfsuite/_fileresource.py
sklearn_crfsuite/compat.py
sklearn_crfsuite/estimator.py
sklearn_crfsuite/metrics.py
sklearn_crfsuite/scorers.py
sklearn_crfsuite/trainer.py
sklearn_crfsuite/utils.py
sklearn_pycrfsuite.egg-info/PKG-INFO
sklearn_pycrfsuite.egg-info/SOURCES.txt
sklearn_pycrfsuite.egg-info/dependency_links.txt
sklearn_pycrfsuite.egg-info/not-zip-safe
sklearn_pycrfsuite.egg-info/requires.txt
sklearn_pycrfsuite.egg-info/top_level.txt
tests/conftest.py
tests/test_crf.py
tests/test_metrics.py