Metadata-Version: 1.1
Name: sklearn-pycrfsuite
Version: 0.4.0
Summary: CRFsuite (python-crfsuite) wrapper which provides interface simlar to scikit-learn
Home-page: https://github.com/supercoderhawk/sklearn-crfsuite
Author: supercoderhawk, Mikhail Korobov
Author-email: supercoderhawk@gmail.com, kmike84@gmail.com
License: MIT license
Platform: UNKNOWN
Classifier: Development Status :: 3 - Alpha
Classifier: License :: OSI Approved :: MIT License
Classifier: Intended Audience :: Developers
Classifier: Operating System :: OS Independent
Classifier: Programming Language :: Python
Classifier: Programming Language :: Python :: 2
Classifier: Programming Language :: Python :: 2.7
Classifier: Programming Language :: Python :: 3
Classifier: Programming Language :: Python :: 3.4
Classifier: Programming Language :: Python :: 3.5
Classifier: Programming Language :: Python :: 3.6
